verbum/__init__.py
verbum/py.typed
verbum/verbum.py
verbum-2.0.0.dist-info/LICENSE
verbum-2.0.0.dist-info/WHEEL
verbum-2.0.0.dist-info/METADATA
verbum-2.0.0.dist-info/RECORD
