Metadata-Version: 2.1
Name: verbum
Version: 2.0.0
Summary: Python version bumper.
Home-page: https://github.com/cielquan/verbum
License: MIT
Keywords: version,pep440
Author: Christian Riedel
Author-email: cielquan@protonmail.com
Requires-Python: >=3.10,<4.0
Classifier: License :: OSI Approved :: MIT License
Classifier: Programming Language :: Python :: 3
Classifier: Programming Language :: Python :: 3.10
Provides-Extra: testing
Requires-Dist: coverage[toml] (>=6.0); extra == "testing"
Requires-Dist: pytest (>=6.0); extra == "testing"
Requires-Dist: pytest-cov (>=3.0); extra == "testing"
Requires-Dist: pytest-randomly (>=3.0); extra == "testing"
Project-URL: Repository, https://github.com/cielquan/verbum
